pydwarf/__about__.py
pydwarf/__init__.py
pydwarf/dwarf.py
pydwarf/util/__about__.py
pydwarf/util/__init__.py
pydwarf/util/dict_utils.py
pydwarf/util/file_extract.py
pydwarf/util/shortencpp.py
pydwarf/util/term_colors.py
pydwarf/util/ver.py
py_dwarf-0.2.2.dist-info/LICENSE
py_dwarf-0.2.2.dist-info/METADATA
py_dwarf-0.2.2.dist-info/WHEEL
py_dwarf-0.2.2.dist-info/top_level.txt
py_dwarf-0.2.2.dist-info/RECORD
