Metadata-Version: 2.1
Name: py-dwarf
Version: 0.2.2
Summary: A package to parse DWARF-formatted debugging information.
Home-page: https://github.com/zcutlip/py-dwarf-parser
License: UNKNOWN
Platform: UNKNOWN
Requires-Python: >=3.7
License-File: LICENSE
